ssl_framework/__init__.py
ssl_framework/main.py
ssl_framework/strategies.py
semi_supervised_learning-0.1.0.dist-info/METADATA
semi_supervised_learning-0.1.0.dist-info/WHEEL
semi_supervised_learning-0.1.0.dist-info/licenses/LICENSE
semi_supervised_learning-0.1.0.dist-info/RECORD
