Metadata-Version: 2.4
Name: semi-supervised-learning
Version: 0.1.0
Summary: Semi-Supervised Learning Framework compatible with scikit-learn
Project-URL: Homepage, https://github.com/yourusername/pyssl
Project-URL: Documentation, https://pyssl.readthedocs.io
Project-URL: Repository, https://github.com/yourusername/pyssl.git
Project-URL: Issues, https://github.com/yourusername/pyssl/issues
Project-URL: Changelog, https://github.com/yourusername/pyssl/releases
Author-email: PySSL Contributors <pyssl@example.com>
Maintainer-email: PySSL Contributors <pyssl@example.com>
License: MIT
License-File: LICENSE
Keywords: machine-learning,pseudo-labeling,scikit-learn,self-training,semi-supervised-learning,ssl
Classifier: Development Status :: 4 - Beta
Classifier: Intended Audience :: Developers
Classifier: Intended Audience :: Science/Research
Classifier: License :: OSI Approved :: MIT License
Classifier: Operating System :: OS Independent
Classifier: Programming Language :: Python :: 3
Classifier: Programming Language :: Python :: 3.8
Classifier: Programming Language :: Python :: 3.9
Classifier: Programming Language :: Python :: 3.10
Classifier: Programming Language :: Python :: 3.11
Classifier: Programming Language :: Python :: 3.12
Classifier: Topic :: Scientific/Engineering :: Artificial Intelligence
Classifier: Topic :: Software Development :: Libraries :: Python Modules
Requires-Python: >=3.8
Requires-Dist: numpy>=1.19.0
Requires-Dist: pandas>=1.2.0
Requires-Dist: scikit-learn>=1.0.0
Provides-Extra: docs
Requires-Dist: myst-parser; extra == 'docs'
Requires-Dist: nbsphinx; extra == 'docs'
Requires-Dist: pydata-sphinx-theme; extra == 'docs'
Requires-Dist: sphinx; extra == 'docs'
Requires-Dist: sphinx-autodoc-typehints; extra == 'docs'
Provides-Extra: test
Requires-Dist: pytest; extra == 'test'
Requires-Dist: pytest-cov; extra == 'test'
